README.md
pyproject.toml
setup.py
mobio/sdks/monitor_system/__main__.py
mobio_monitor_system_sdk.egg-info/PKG-INFO
mobio_monitor_system_sdk.egg-info/SOURCES.txt
mobio_monitor_system_sdk.egg-info/dependency_links.txt
mobio_monitor_system_sdk.egg-info/namespace_packages.txt
mobio_monitor_system_sdk.egg-info/requires.txt
mobio_monitor_system_sdk.egg-info/top_level.txt